yamas/__init__.py
yamas/config.json
yamas/create_visualization.py
yamas/dataset_downloading.py
yamas/export_data.py
yamas/fastq_visualization.py
yamas/prerun_configs.py
yamas/qiita_visualization.py
yamas/utilities.py
YMS-1.2.14.dist-info/METADATA
YMS-1.2.14.dist-info/WHEEL
YMS-1.2.14.dist-info/entry_points.txt
YMS-1.2.14.dist-info/top_level.txt
YMS-1.2.14.dist-info/RECORD
