Metadata-Version: 2.1
Name: YMS
Version: 1.2.14
Summary: YOLO Microbiome Analysis System
Home-page: UNKNOWN
Author: Yarin Bekor, Shani Finkelstein
Author-email: yarin.bekor@gmail.com, shaninn123@gmail.com
License: MIT
Platform: UNKNOWN
Requires-Dist: MetaPhlAn
Requires-Dist: tqdm
